pypise/__init__.py
pypise/case.py
pypise/driver.py
pypise/pypise_api.py
pypise/running/HTML_test_runner.py
pypise/running/__init__.py
pypise/running/test_runner.py
pypise-0.0.1.dist-info/LICENSE
pypise-0.0.1.dist-info/METADATA
pypise-0.0.1.dist-info/WHEEL
pypise-0.0.1.dist-info/entry_points.txt
pypise-0.0.1.dist-info/top_level.txt
pypise-0.0.1.dist-info/RECORD
