Metadata-Version: 2.1
Name: pypise
Version: 0.0.1
Summary: WebUI automation testing framework based on Selenium and unittest.
Home-page: https://github.com/gerrywen/pypise.git
Author: gerrywen
Author-email: blog@gerrywen.com
License: MIT
Keywords: pypise pypise selenium testcase unittest
Platform: UNKNOWN
Classifier: Programming Language :: Python :: 3.5
Classifier: Programming Language :: Python :: 3.6
Classifier: Programming Language :: Python :: 3.7
